florestdevtools/__init__.py
florestdevtools/discord_utilits.py
florestdevtools/utilits.py
florestdevtools-0.0.1a0.dist-info/METADATA
florestdevtools-0.0.1a0.dist-info/WHEEL
florestdevtools-0.0.1a0.dist-info/top_level.txt
florestdevtools-0.0.1a0.dist-info/RECORD
